grr/__init__.py
grr/commit-msg
grr-1.0.2.dist-info/COPYING
grr-1.0.2.dist-info/METADATA
grr-1.0.2.dist-info/WHEEL
grr-1.0.2.dist-info/entry_points.txt
grr-1.0.2.dist-info/top_level.txt
grr-1.0.2.dist-info/RECORD
