Metadata-Version: 2.1
Name: grr
Version: 1.0.2
Summary: A command-line utility to work with Gerrit
Home-page: https://github.com/legoktm/grr/
Author: Kunal Mehta
Author-email: legoktm@member.fsf.org
License: GPL-3.0-or-later
Platform: UNKNOWN
Requires-Python: >=3.5
